README.rst
setup.cfg
setup.py
spanky/__init__.py
spanky/cli.py
spanky/config.py
spanky.egg-info/PKG-INFO
spanky.egg-info/SOURCES.txt
spanky.egg-info/dependency_links.txt
spanky.egg-info/entry_points.txt
spanky.egg-info/not-zip-safe
spanky.egg-info/requires.txt
spanky.egg-info/top_level.txt