Metadata-Version: 1.1
Name: spanky
Version: 0.1.0
Summary: Idempotent devops
Home-page: https://github.com/ionrock/spanky
Author: Eric Larson
Author-email: eric@ionrock.org
License: BSD
Keywords: spanky
Platform: UNKNOWN
Classifier: Development Status :: 2 - Pre-Alpha
Classifier: Intended Audience :: Developers
Classifier: License :: OSI Approved :: BSD License
Classifier: Natural Language :: English
Classifier: Programming Language :: Python :: 2
Classifier: Programming Language :: Python :: 2.6
Classifier: Programming Language :: Python :: 2.7
Classifier: Programming Language :: Python :: 3
Classifier: Programming Language :: Python :: 3.3
Classifier: Programming Language :: Python :: 3.4
